{
  "gitSyncId": "641a8da5a8db493ee062abbb_2023-03-22T12:11:37.223470046Z",
  "id": "Customer Data_DeleteQuery",
  "pluginId": "mongo-plugin",
  "pluginType": "DB",
  "unpublishedAction": {
    "actionConfiguration": {
      "body": "",
      "encodeParamsToggle": true,
      "formData": {
        "collection": {
          "componentData": "Customers",
          "data": "Customers",
          "viewType": "component"
        },
        "command": {
          "componentData": "DELETE",
          "data": "DELETE",
          "viewType": "component"
        },
        "delete": {
          "limit": {
            "componentData": "SINGLE",
            "data": "SINGLE",
            "viewType": "component"
          },
          "query": {
            "componentData": "{ _id: ObjectId('{{data_table.triggeredRow._id}}') }",
            "data": "{ _id: ObjectId('{{data_table.triggeredRow._id}}') }",
            "viewType": "component"
          }
        },
        "smartSubstitution": {
          "componentData": true,
          "data": true,
          "viewType": "component"
        }
      },
      "paginationType": "NONE",
      "path": "template_table/{{data_table.selectedRow._ref}}",
      "timeoutInMillisecond": 10000
    },
    "confirmBeforeExecute": false,
    "datasource": {
      "id": "Mongo_MarketingDB",
      "isAutoGenerated": false,
      "name": "Mongo_MarketingDB",
      "pluginId": "mongo-plugin"
    },
    "executeOnLoad": false,
    "name": "DeleteQuery",
    "pageId": "Customer Data",
    "userSetOnLoad": false
  }
}